LICENSE
README.md
pyproject.toml
setup.py
donutshell/__init__.py
donutshell/__main__.py
donutshell.egg-info/PKG-INFO
donutshell.egg-info/SOURCES.txt
donutshell.egg-info/dependency_links.txt
donutshell.egg-info/entry_points.txt
donutshell.egg-info/requires.txt
donutshell.egg-info/top_level.txt
donutshell/builtin_modules/__init__.py
donutshell/builtin_modules/clear.py
donutshell/builtin_modules/echo.py
donutshell/builtin_modules/ls.py
donutshell/utils/__init__.py
donutshell/utils/command_not_found.py
donutshell/utils/help_console.py
donutshell/utils/read_config.py