Metadata-Version: 2.1
Name: donutshell
Version: 0.0.1rc3
Summary: A Shell built-in Python but not meant for daily use.
Home-page: https://github.com/loldonut/donutshell
Author: loldonut
License: MIT
Keywords: shell,terminal,console
Platform: UNKNOWN
Classifier: Development Status :: 3 - Alpha
Classifier: Environment :: Console
Classifier: Topic :: System :: Shells
Classifier: License :: OSI Approved :: MIT License
Classifier: Programming Language :: Python
Classifier: Programming Language :: Python :: 3.8
Classifier: Typing :: Typed
License-File: LICENSE
